WeiShengwuXinxixueShejiDePythonJiaocheng/README.md
WeiShengwuXinxixueShejiDePythonJiaocheng/__init__.py
WeiShengwuXinxixueShejiDePythonJiaocheng/__main__.py
WeiShengwuXinxixueShejiDePythonJiaocheng/file.epub
WeiShengwuXinxixueShejiDePythonJiaocheng/index.html
WeiShengwuXinxixueShejiDePythonJiaocheng/css/__init__.py
WeiShengwuXinxixueShejiDePythonJiaocheng/css/annotations.css
WeiShengwuXinxixueShejiDePythonJiaocheng/css/main.css
WeiShengwuXinxixueShejiDePythonJiaocheng/css/normalize.css
WeiShengwuXinxixueShejiDePythonJiaocheng/css/popup.css
WeiShengwuXinxixueShejiDePythonJiaocheng/font/__init__.py
WeiShengwuXinxixueShejiDePythonJiaocheng/font/fontello.eot
WeiShengwuXinxixueShejiDePythonJiaocheng/font/fontello.svg
WeiShengwuXinxixueShejiDePythonJiaocheng/font/fontello.ttf
WeiShengwuXinxixueShejiDePythonJiaocheng/font/fontello.woff
WeiShengwuXinxixueShejiDePythonJiaocheng/img/__init__.py
WeiShengwuXinxixueShejiDePythonJiaocheng/img/annotator-glyph-sprite.png
WeiShengwuXinxixueShejiDePythonJiaocheng/img/annotator-icon-sprite.png
WeiShengwuXinxixueShejiDePythonJiaocheng/img/apple-touch-icon.png
WeiShengwuXinxixueShejiDePythonJiaocheng/img/cancelfullscreen.png
WeiShengwuXinxixueShejiDePythonJiaocheng/img/close.png
WeiShengwuXinxixueShejiDePythonJiaocheng/img/fullscreen.png
WeiShengwuXinxixueShejiDePythonJiaocheng/img/loader.gif
WeiShengwuXinxixueShejiDePythonJiaocheng/img/menu-icon.png
WeiShengwuXinxixueShejiDePythonJiaocheng/img/save.png
WeiShengwuXinxixueShejiDePythonJiaocheng/img/saved.png
WeiShengwuXinxixueShejiDePythonJiaocheng/img/settings-s.png
WeiShengwuXinxixueShejiDePythonJiaocheng/img/settings.png
WeiShengwuXinxixueShejiDePythonJiaocheng/img/star.png
WeiShengwuXinxixueShejiDePythonJiaocheng/js/__init__.py
WeiShengwuXinxixueShejiDePythonJiaocheng/js/epub.js
WeiShengwuXinxixueShejiDePythonJiaocheng/js/epub.min.js
WeiShengwuXinxixueShejiDePythonJiaocheng/js/epub.min.map
WeiShengwuXinxixueShejiDePythonJiaocheng/js/hooks.min.js
wei_shengwu_xinxixue_sheji_de_python_jiaocheng-2024.3.2.0.dist-info/METADATA
wei_shengwu_xinxixue_sheji_de_python_jiaocheng-2024.3.2.0.dist-info/WHEEL
wei_shengwu_xinxixue_sheji_de_python_jiaocheng-2024.3.2.0.dist-info/entry_points.txt
wei_shengwu_xinxixue_sheji_de_python_jiaocheng-2024.3.2.0.dist-info/top_level.txt
wei_shengwu_xinxixue_sheji_de_python_jiaocheng-2024.3.2.0.dist-info/RECORD
